equiassign/__init__.py
equiassign/equiassign.py
equitable_assign-22.8.0.dist-info/LICENSE
equitable_assign-22.8.0.dist-info/METADATA
equitable_assign-22.8.0.dist-info/WHEEL
equitable_assign-22.8.0.dist-info/top_level.txt
equitable_assign-22.8.0.dist-info/RECORD
