Metadata-Version: 2.1
Name: equitable-assign
Version: 22.8.0
Summary: Generate random assignments of workers to tasks and balance each worker's load
Author-email: Shawheen Naderi <snaderi@csus.edu>, Clark Fitzgerald <fitzgerald@csus.edu>
License: MIT License        
Project-URL: Homepage, https://github.com/clarkfitzg/equitable-assign
Project-URL: Bug Tracker, https://github.com/clarkfitzg/equitable-assign/issues
Classifier: Programming Language :: Python :: 3
Classifier: License :: OSI Approved :: MIT License
Classifier: Operating System :: OS Independent
Requires-Python: >=3.7
License-File: LICENSE
